MANIFEST.in
README.rst
setup.py
anybox/__init__.py
anybox.paster.openerp.egg-info/PKG-INFO
anybox.paster.openerp.egg-info/SOURCES.txt
anybox.paster.openerp.egg-info/dependency_links.txt
anybox.paster.openerp.egg-info/entry_points.txt
anybox.paster.openerp.egg-info/namespace_packages.txt
anybox.paster.openerp.egg-info/not-zip-safe
anybox.paster.openerp.egg-info/requires.txt
anybox.paster.openerp.egg-info/top_level.txt
anybox/paster/__init__.py
anybox/paster/openerp/__init__.py
anybox/paster/openerp/instance.py
anybox/paster/openerp/module.py
anybox/paster/openerp/templates/instance/bootstrap.py
anybox/paster/openerp/templates/instance/buildout.cfg_tmpl
anybox/paster/openerp/templates/instance/buildout.dev.cfg
anybox/paster/openerp/templates/instance/addons/+package+/__init__.py
anybox/paster/openerp/templates/instance/addons/+package+/__openerp__.py_tmpl
anybox/paster/openerp/templates/instance/addons/+package+/security/ir.model.access.csv
anybox/paster/openerp/templates/instance/addons/+package+/static/src/img/icon.png
anybox/paster/openerp/templates/instance/addons/+package+/tests/__init__.py
anybox/paster/openerp/templates/instance/addons/+package+/view/menu.xml
anybox/paster/openerp/templates/module/__init__.py_tmpl
anybox/paster/openerp/templates/module/__openerp__.py_tmpl
anybox/paster/openerp/templates/module/i18n/fr.po_tmpl
anybox/paster/openerp/templates/module/security/ir.model.access.csv
anybox/paster/openerp/templates/module/static/src/img/icon.png
anybox/paster/openerp/templates/module/view/menu.xml_tmpl
anybox_openerp/__init__.py