Metadata-Version: 1.0
Name: anybox.paster.openerp
Version: 0.6
Summary: Paster templates to create an OpenERP module or instance using buildout
Home-page: http://anybox.fr
Author: Anybox
Author-email: jssuzanne@anybox.fr
License: GPL v3
Keywords: OpenERP,paster
Platform: UNKNOWN
